README.rst
setup.py
vimeo/__init__.py
vimeo/client.py
vimeo.egg-info/PKG-INFO
vimeo.egg-info/SOURCES.txt
vimeo.egg-info/dependency_links.txt
vimeo.egg-info/requires.txt
vimeo.egg-info/top_level.txt