Metadata-Version: 1.0
Name: vimeo
Version: 0.1.8
Summary: Python module for using Vimeo API.
Home-page: https://github.com/rkumarnirmal/python-vimeo
Author: Nirmal Kumar
Author-email: rkumarnirmal@gmail.com
License: MIT
Keywords: vimeo internet api
Platform: UNKNOWN
Classifier: Development Status :: 4 - Beta
Classifier: Intended Audience :: Developers
Classifier: License :: OSI Approved :: MIT License
Classifier: Operating System :: OS Independent
Classifier: Programming Language :: Python
Classifier: Topic :: Internet
Classifier: Topic :: Multimedia :: Video
Classifier: Topic :: Software Development :: Libraries :: Python Modules
